setup.py
domingo/__init__.py
domingo/connection.py
domingo/data_access.py
domingo/exceptions.py
domingo/fields.py
domingo/models.py
domingo/query.py
domingo/support.py
domingo/utils.py
domingo.egg-info/PKG-INFO
domingo.egg-info/SOURCES.txt
domingo.egg-info/dependency_links.txt
domingo.egg-info/requires.txt
domingo.egg-info/top_level.txt
domingo/backends/__init__.py
domingo/backends/base.py
domingo/backends/mock_backend.py
domingo/backends/mongo_backend.py
domingo/backends/redis_backend.py
domingo/backends/rethink_backend.py
domingo/contrib/__init__.py
domingo/contrib/django/__init__.py
domingo/contrib/django/fields.py
domingo/contrib/django/models.py
domingo/contrib/django/tests/__init__.py
domingo/tests/__init__.py
domingo/tests/test_fields.py
domingo/tests/test_models.py
domingo/tests/test_mongo_backend.py
domingo/tests/test_utils.py