Metadata-Version: 1.1
Name: domingo
Version: 1.1.5
Summary: A django-like modelling interface for various schemaless dbs
Home-page: https://github.com/hangarunderground/domingo
Author: hangarunderground
Author-email: domingo@reelio.com
License: UNKNOWN
Download-URL: https://github.com/hangarunderground/domingo/tarball/1.1.5
Keywords: django,schema-less,models,data
Platform: UNKNOWN
Classifier: Development Status :: 4 - Beta
Classifier: Framework :: Django
Classifier: Intended Audience :: Developers
Classifier: License :: OSI Approved :: MIT License
Classifier: Operating System :: POSIX
Classifier: Programming Language :: Python
Classifier: Topic :: Internet :: WWW/HTTP
